CHANGES.txt
CONTRIBUTORS.txt
COPYRIGHT.txt
LICENSE.txt
MANIFEST.in
README.rst
setup.cfg
setup.py
pyramid_extdirect/__init__.py
pyramid_extdirect.egg-info/PKG-INFO
pyramid_extdirect.egg-info/SOURCES.txt
pyramid_extdirect.egg-info/dependency_links.txt
pyramid_extdirect.egg-info/entry_points.txt
pyramid_extdirect.egg-info/not-zip-safe
pyramid_extdirect.egg-info/requires.txt
pyramid_extdirect.egg-info/top_level.txt