Metadata-Version: 1.1
Name: pyramid-extdirect
Version: 0.6.0
Summary: ExtDirect Implementation for Pyramid
Home-page: http://github.com/jenner/pyramid_extdirect
Author: Igor Stroh
Author-email: igor.stroh@rulim.de
License: BSD-derived (http://www.repoze.org/LICENSE.txt)
Keywords: web wsgi javascript pyramid extdirect
Platform: UNKNOWN
Classifier: Intended Audience :: Developers
Classifier: Programming Language :: Python
Classifier: Framework :: Pylons
Classifier: License :: Repoze Public License
